{
  "date": "2026-07-20",
  "generated_at": "2026-07-20T15:20:40.714826+00:00",
  "source": "sspai",
  "count": 10,
  "columns": [
    {
      "name": "标题",
      "key": "title",
      "type": "link",
      "hrefKey": "url"
    },
    {
      "name": "概要",
      "key": "summary",
      "type": "text"
    },
    {
      "name": "作者",
      "key": "author",
      "type": "text",
      "hide": true
    },
    {
      "name": "标签",
      "key": "tags",
      "type": "taglist"
    }
  ],
  "items": [
    {
      "title": "派评 | 近期值得关注的 App",
      "url": "https://sspai.com/post/112543",
      "summary": ">下载少数派2.0客户端、关注少数派公众号，解锁全新阅读体验📰>实用、好用的正版软件，少数派为你呈现🚀查看全文",
      "author": "少数派编辑部",
      "tags": []
    },
    {
      "title": "角落新声 | 把杂乱桌面收拾得像样，只需要一张桌垫",
      "url": "https://sspai.com/post/112453",
      "summary": "在拥有你我理想的超大自主空间之前，不如用一张桌垫改善一下自己的工作生活环境，过得多舒心一点点吧。查看全文",
      "author": "北鸮",
      "tags": []
    },
    {
      "title": "2026 年再看 iPhone 8 Plus，它还够用吗？",
      "url": "https://sspai.com/post/112425",
      "summary": "高考结束后，又有一大批同学开始考虑换新手机啦。在预算差不多的情况下，很多人会纠结是买一台较新的中端机，还是买一台年份更老、但曾经是旗舰级的机型。于是我把 2020 年购入的 iPhone 8 Plus 拿出来当了一星期主力机，看看这台 2017 年发布的手机，放到今天还能不能胜任日常使用。查看全文",
      "author": "旋转的陀螺",
      "tags": []
    },
    {
      "title": "派早报：锂电池消费税分阶段恢复征收",
      "url": "https://sspai.com/post/112498",
      "summary": "锂电池消费税分阶段恢复征收白宫提词器操作员利用内幕信息下注被查LG 显示器连接电脑后自动安装广告程序新一代豆包手机不再模拟点击操作亚马逊错发数亿美元云服务账单京沪线试点 12306 预约购票，最早提前 60 天看看就行的小道消息少数派的近期动态你可能错过的好文章查看全文",
      "author": "少数派编辑部",
      "tags": []
    },
    {
      "title": "TDS REVIEW | 索尼 WH-1000XX 无线降噪头戴耳机体验",
      "url": "https://sspai.com/post/112374",
      "summary": "这篇文章是TDSStudio在少数派上的第26篇文章，依然是全平台首发。1000XTheColleXion，这是索尼1000X系列的十周年纪念产品线。完全想不到跟群友们畅聊MDR-1000X的时代已经 ...查看全文",
      "author": "KingTsui",
      "tags": []
    },
    {
      "title": "小米 NAS 拆解与初步上手：它会是你的第一台 NAS 吗？",
      "url": "https://sspai.com/post/112398",
      "summary": "小米智能存储最适合两类用户：家里已经有较多米家设备的人，以及小米手机用户。查看全文",
      "author": "羊刀仙",
      "tags": []
    },
    {
      "title": "本周看什么 | 最近值得一看的 10 部作品",
      "url": "https://sspai.com/post/112444",
      "summary": "📅本周新预告《蓦然回首》正式预告7月15日，电影《蓦然回首》发布了正式预告，将于9月11日在日本上映。是枝裕和执导、编剧、剪辑，出口夏希、莳田彩珠主演，菅田将晖、宫藤官九郎、野吕佳代、山田真步等出演， ...查看全文",
      "author": "少数派编辑部",
      "tags": []
    },
    {
      "title": "具透 | watchOS 27 公测版一览：动态应用网格、Liquid Glass 微调……",
      "url": "https://sspai.com/post/112430",
      "summary": "AI 之外，watchOS 27 中还有这些新功能。查看全文",
      "author": "少数派编辑部",
      "tags": []
    },
    {
      "title": "UniGetUI：可能是 Windows 下最好用的应用商店",
      "url": "https://sspai.com/post/111128",
      "summary": "UniGetUI 是一个不错的包管理器，它提供的统一的更新 UI，让你的软件最大程度集中在一起管理，还可以用于需要批量配置的场景。查看全文",
      "author": "Bestony",
      "tags": []
    },
    {
      "title": "派早报：OPPO 宣布调整旗下子品牌的全球产品策略等",
      "url": "https://sspai.com/post/112414",
      "summary": "月之暗面发布 Kimi K3 模型，支付宝升级 Apple 教育优惠认证等。查看全文",
      "author": "少数派编辑部",
      "tags": []
    }
  ]
}