{
  "date": "2026-07-19",
  "generated_at": "2026-07-19T14:35:34.368873+00:00",
  "source": "ftchinese",
  "count": 20,
  "columns": [
    {
      "name": "标题",
      "key": "title",
      "type": "link",
      "hrefKey": "url"
    },
    {
      "name": "概要",
      "key": "summary",
      "type": "text"
    },
    {
      "name": "作者",
      "key": "author",
      "type": "text",
      "hide": true
    },
    {
      "name": "标签",
      "key": "tags",
      "type": "taglist"
    }
  ],
  "items": [
    {
      "title": "失守中国市场，德国汽车业将迎来怎样的连锁反应？",
      "url": "https://www.ftchinese.com/story/001110357",
      "summary": "张冬方：对德国汽车业来说，中国市场“牵一发而动全身”，他们甚至已然嗅到了“全盘皆输”的危险气息。",
      "author": "",
      "tags": []
    },
    {
      "title": "大跌之后，科技股盛宴结束了吗？",
      "url": "https://www.ftchinese.com/story/001110356",
      "summary": "徐瑾：“黑色星期五”，环球市场大跌。有人高喊加仓，有人感叹牛市终结。如何看待这次下跌？科技股的春天结束了吗？手握现金的巴菲特，其忠告有何启发？",
      "author": "",
      "tags": []
    },
    {
      "title": "人工智能大会开幕，中国设立人工智能治理新机构",
      "url": "https://www.ftchinese.com/story/001110354",
      "summary": "总部在上海的新机构“世界人工智能合作组织”将增强中国在国际标准制定及其他问题上的影响力。",
      "author": "",
      "tags": []
    },
    {
      "title": "中期选举临近，特朗普重提大选干预论",
      "url": "https://www.ftchinese.com/story/001110353",
      "summary": "特朗普重提毫无根据的2020年大选干预论，在中期选举之前制造民众对美国选举公正性的怀疑。",
      "author": "",
      "tags": []
    },
    {
      "title": "快递业告别价格战？“反内卷”成效待利润验证",
      "url": "https://www.ftchinese.com/story/001110352",
      "summary": "咏竹坊：中国快递业反内卷初见成效，单票收入止跌回升，但企业盈利与股价表现分化，价格修复能否持续仍待观察。",
      "author": "",
      "tags": []
    },
    {
      "title": "工业革命催生了工会，1300万第一代移民又将催生什么？",
      "url": "https://www.ftchinese.com/story/001110351",
      "summary": "何越：新的社会现实所要求的，是一种能够深入地方社会、跨越语言与文化、帮助已定居的第一代移民进入公共生活的新型民主组织。",
      "author": "",
      "tags": []
    },
    {
      "title": "IMF：英国已无力增加公共支出",
      "url": "https://www.ftchinese.com/story/001110350",
      "summary": "国际货币基金组织提醒新首相伯纳姆，鉴于英国预算前景“充满挑战”，针对能源账单的任何资助都需要通过其他领域的节省来抵消。",
      "author": "",
      "tags": []
    },
    {
      "title": "《奥德赛》：为何要让“拍摄史诗”成为史诗？",
      "url": "https://www.ftchinese.com/story/001110347",
      "summary": "魏宁均：《奥德赛》是一部史诗电影，它的拍摄过程本身也如同一部史诗，凝聚着电影人重塑创作灵光的努力。正如史诗作品总是可一而不可再的，每一次拍摄也都可能成为最后一次。",
      "author": "",
      "tags": []
    },
    {
      "title": "美加墨世界杯札记之六：因凡蒂诺的权术，主教练的运气",
      "url": "https://www.ftchinese.com/story/001110346",
      "summary": "范力文：尽管批判之声不绝于耳，但国际足联主席似乎从不羞于承认并践行权力的逻辑；对于球队主帅的抨击则常常是后见之明，一个决策的成与败，未必在于其本身的高下，而是源于运气。",
      "author": "",
      "tags": []
    },
    {
      "title": "艺术大师莫兰迪：瓶瓶罐罐后的精神秘密",
      "url": "https://www.ftchinese.com/story/001110342",
      "summary": "薛莉：1915年，25岁的莫兰迪参加“一战”，因病退役。墨索里尼在位的20年，正是他人生的黄金时代。在最动荡的年月，他是怎么过来的？",
      "author": "",
      "tags": []
    },
    {
      "title": "谁让艺术被看见、被相信、被留下？",
      "url": "https://www.ftchinese.com/story/001110339",
      "summary": "朱永磊：什么样的艺术能够进入视野？什么样的艺术会被认真对待？什么样的艺术最终能够留下？权力一直都在，只是不断更换形状。",
      "author": "",
      "tags": []
    },
    {
      "title": "欧洲野火肆虐 法国过火面积创历史新高",
      "url": "https://www.ftchinese.com/story/001110349",
      "summary": "随着欧洲多地遭遇连番热浪和干旱，起火风险急剧上升。FT分析显示，法国今年的野火过火面积超过4.1万公顷，四倍于平均水平。",
      "author": "",
      "tags": []
    },
    {
      "title": "伯纳姆：拒戴领带的英国首相和他的北方故事",
      "url": "https://www.ftchinese.com/story/001110332",
      "summary": "静楠：英国当下的挑战，不仅是地区发展失衡，还包括财政空间有限、人口老龄化、劳动生产率长期停滞，以及人工智能带来的就业结构重构。",
      "author": "",
      "tags": []
    },
    {
      "title": "支持冒险或放大浪费：地方引导基金该怎样投向未来产业？",
      "url": "https://www.ftchinese.com/story/001110334",
      "summary": "李学楠、王小龙：一体两面的问题显而易见。地方产业资本可以成为支持企业家冒险的“临门一脚”，也可能变成换了外壳的新型补贴，甚至造成低效投入。",
      "author": "",
      "tags": []
    },
    {
      "title": "算力经济性的中国命题",
      "url": "https://www.ftchinese.com/story/001110335",
      "summary": "王嘉诚：2026年“算电协同”首次写入政府工作报告，标志着算力经济性从行业共识上升为国家战略。对中国算力企业而言，这既是政策东风，也是技术路线的校准器。",
      "author": "",
      "tags": []
    },
    {
      "title": "从美俄军事实践看现代非对称战争的局限性",
      "url": "https://www.ftchinese.com/story/001110340",
      "summary": "王英良：美俄困境是时代必然，国内政治与全球化从内外双向约束大国武力。世界正从霸权走向均衡，武力带来的收益更加充满风险。",
      "author": "",
      "tags": []
    },
    {
      "title": "夜色正浓：经济下行时代的罗曼史",
      "url": "https://www.ftchinese.com/story/001110309",
      "summary": "徐瑾：当经济的潮水散去，人性的底色也会暴露。人才为何变为耗材，打工人如何成为牛马，大企业如何褪去光环？工作和尊严，真的只能选一个？",
      "author": "",
      "tags": []
    },
    {
      "title": "美国议员敦促特朗普政府禁止美国企业采购中国存储芯片",
      "url": "https://www.ftchinese.com/story/001110348",
      "summary": "议员敦促特朗普政府禁止美国企业向长鑫存储和长江存储采购存储芯片，以避免在人工智能基础设施的关键组件上依赖中国。",
      "author": "",
      "tags": []
    },
    {
      "title": "巴拿马官员赴北京，寻求化解船舶扣留争端",
      "url": "https://www.ftchinese.com/story/001110345",
      "summary": "中国加大对巴拿马籍船舶的扣留力度后，大批船舶正迅速退出巴拿马船籍。中方表示，这些扣留均与安全问题相关。",
      "author": "",
      "tags": []
    },
    {
      "title": "可灵估值180亿美元 快手AI王牌单飞倒计时",
      "url": "https://www.ftchinese.com/story/001110344",
      "summary": "快手把可灵推向资本市场，为AI视频资产打开新的估值空间。",
      "author": "",
      "tags": []
    }
  ]
}